c7n_mailer/__init__.py
c7n_mailer/cli.py
c7n_mailer/datadog_delivery.py
c7n_mailer/deploy.py
c7n_mailer/email_delivery.py
c7n_mailer/graph_delivery.py
c7n_mailer/handle.py
c7n_mailer/ldap_lookup.py
c7n_mailer/replay.py
c7n_mailer/slack_delivery.py
c7n_mailer/smtp_delivery.py
c7n_mailer/sns_delivery.py
c7n_mailer/splunk_delivery.py
c7n_mailer/sqs_queue_processor.py
c7n_mailer/target.py
c7n_mailer/utils.py
c7n_mailer/utils_email.py
c7n_mailer/azure_mailer/__init__.py
c7n_mailer/azure_mailer/azure_queue_processor.py
c7n_mailer/azure_mailer/deploy.py
c7n_mailer/azure_mailer/function.py
c7n_mailer/azure_mailer/handle.py
c7n_mailer/azure_mailer/sendgrid_delivery.py
c7n_mailer/azure_mailer/utils.py
c7n_mailer/gcp_mailer/__init__.py
c7n_mailer/gcp_mailer/gcp_queue_processor.py
c7n_mailer/gcp_mailer/utils.py
c7n_mailer/msg-templates/default.html.j2
c7n_mailer/msg-templates/default.j2
c7n_mailer/msg-templates/slack_default.j2
c7n_mailer-0.6.48.dist-info/METADATA
c7n_mailer-0.6.48.dist-info/WHEEL
c7n_mailer-0.6.48.dist-info/entry_points.txt
c7n_mailer-0.6.48.dist-info/RECORD
