Metadata-Version: 2.4
Name: c7n_mailer
Version: 0.6.48
Summary: Cloud Custodian - Reference Mailer
Project-URL: homepage, https://cloudcustodian.io
Project-URL: repository, https://github.com/cloud-custodian/cloud-custodian
Project-URL: documentation, https://cloudcustodian.io/docs/
Author: Cloud Custodian Project
License-Expression: Apache-2.0
Classifier: License :: OSI Approved :: Apache Software License
Classifier: Topic :: System :: Distributed Computing
Classifier: Topic :: System :: Systems Administration
Requires-Python: <4.0.0,>=3.9.2
Requires-Dist: boto3 ==1.42.27
Requires-Dist: datadog ==0.52.1
Requires-Dist: importlib-metadata ==8.7.1
Requires-Dist: jinja2 ==3.1.6
Requires-Dist: jsonpatch ==1.33
Requires-Dist: jsonpointer ==3.0.0
Requires-Dist: jsonschema ==4.26.0
Requires-Dist: ldap3 ==2.9.1
Requires-Dist: python-dateutil ==2.9.0.post0
Requires-Dist: pyyaml ==6.0.3
Requires-Dist: redis ==5.3.1
Requires-Dist: sendgrid ==6.12.4
Requires-Dist: types-six ==1.17.0.20251009
Provides-Extra: azure
Requires-Dist: c7n-azure ==0.7.48; extra == 'azure'
Provides-Extra: gcp
Requires-Dist: c7n-gcp ==0.4.48; extra == 'gcp'
Requires-Dist: google-cloud-secret-manager ==2.26.0; extra == 'gcp'
